toloka/__init__.py
toloka/__init__.pyi
toloka/__version__.py
toloka/py.typed
toloka/async_client/__init__.py
toloka/async_client/__init__.pyi
toloka/async_client/client.py
toloka/async_client/client.pyi
toloka/autoquality/__init__.py
toloka/autoquality/__init__.pyi
toloka/autoquality/optimizer.py
toloka/autoquality/optimizer.pyi
toloka/autoquality/scoring.py
toloka/autoquality/scoring.pyi
toloka/client/__init__.py
toloka/client/__init__.pyi
toloka/client/_converter.py
toloka/client/_converter.pyi
toloka/client/actions.py
toloka/client/actions.pyi
toloka/client/aggregation.py
toloka/client/aggregation.pyi
toloka/client/analytics_request.py
toloka/client/analytics_request.pyi
toloka/client/assignment.py
toloka/client/assignment.pyi
toloka/client/attachment.py
toloka/client/attachment.pyi
toloka/client/batch_create_results.py
toloka/client/batch_create_results.pyi
toloka/client/clone_results.py
toloka/client/clone_results.pyi
toloka/client/collectors.py
toloka/client/collectors.pyi
toloka/client/conditions.py
toloka/client/conditions.pyi
toloka/client/error_codes.py
toloka/client/error_codes.pyi
toloka/client/exceptions.py
toloka/client/exceptions.pyi
toloka/client/filter.py
toloka/client/filter.pyi
toloka/client/message_thread.py
toloka/client/message_thread.pyi
toloka/client/operation_log.py
toloka/client/operation_log.pyi
toloka/client/operations.py
toloka/client/operations.pyi
toloka/client/owner.py
toloka/client/owner.pyi
toloka/client/py.typed
toloka/client/quality_control.py
toloka/client/quality_control.pyi
toloka/client/requester.py
toloka/client/requester.pyi
toloka/client/search_requests.py
toloka/client/search_requests.pyi
toloka/client/search_results.py
toloka/client/search_results.pyi
toloka/client/skill.py
toloka/client/skill.pyi
toloka/client/solution.py
toloka/client/solution.pyi
toloka/client/task.py
toloka/client/task.pyi
toloka/client/task_distribution_function.py
toloka/client/task_distribution_function.pyi
toloka/client/task_suite.py
toloka_kit-1.2.3.dist-info/AUTHORS
toloka_kit-1.2.3.dist-info/LICENSE
toloka_kit-1.2.3.dist-info/METADATA
toloka_kit-1.2.3.dist-info/WHEEL
toloka_kit-1.2.3.dist-info/top_level.txt
toloka_kit-1.2.3.dist-info/RECORD
