Metadata-Version: 2.1
Name: toloka-kit
Version: 1.2.3
Summary: Toloka API client
Author: Vladimir Losev
Author-email: losev@yandex-team.ru
License: Apache 2.0
Project-URL: Documentation, https://toloka.ai/docs/toloka-kit
Project-URL: Source, https://github.com/Toloka/toloka-kit
Classifier: Development Status :: 5 - Production/Stable
Classifier: Intended Audience :: Developers
Classifier: Intended Audience :: Science/Research
Classifier: License :: OSI Approved :: Apache Software License
Classifier: Operating System :: OS Independent
Classifier: Programming Language :: Python
Classifier: Programming Language :: Python :: 3
Classifier: Programming Language :: Python :: 3.8
Classifier: Programming Language :: Python :: 3.9
Classifier: Programming Language :: Python :: 3.10
Classifier: Programming Language :: Python :: 3.11
Classifier: Programming Language :: Python :: Implementation :: CPython
Classifier: Topic :: Scientific/Engineering
Classifier: Topic :: Software Development
Classifier: Typing :: Typed
Requires-Python: >=3.8.0
License-File: LICENSE
License-File: AUTHORS
Requires-Dist: attrs>=20.3.0
Requires-Dist: cattrs>=1.9
Requires-Dist: cached-property; python_version < "3.8.0"
Requires-Dist: filelock>=3.2.0
Requires-Dist: requests
Requires-Dist: httpx
Requires-Dist: tenacity<8.3,>=7.0
Requires-Dist: typing-extensions
Requires-Dist: urllib3>=1.26.0
Requires-Dist: simplejson
Requires-Dist: docstring-parser
Requires-Dist: tqdm
Provides-Extra: dev
Requires-Dist: aiohttp; extra == "dev"
Requires-Dist: data-science-types; extra == "dev"
Requires-Dist: flake8; extra == "dev"
Requires-Dist: mypy; extra == "dev"
Requires-Dist: pytest; extra == "dev"
Requires-Dist: pytest-asyncio; extra == "dev"
Requires-Dist: pytest-lazy-fixture; extra == "dev"
Requires-Dist: pytest-mock; extra == "dev"
Requires-Dist: pytest-timeout; extra == "dev"
Requires-Dist: respx; extra == "dev"
Requires-Dist: tox; extra == "dev"
Requires-Dist: types-urllib3; extra == "dev"
Provides-Extra: pandas
Requires-Dist: pandas; extra == "pandas"
Provides-Extra: autoquality
Requires-Dist: crowd-kit>=1.0.0; extra == "autoquality"
Provides-Extra: s3
Requires-Dist: boto3>=1.4.7; extra == "s3"
Provides-Extra: zookeeper
Requires-Dist: kazoo>=2.6.1; extra == "zookeeper"
Provides-Extra: jupyter-metrics
Requires-Dist: plotly; extra == "jupyter-metrics"
Requires-Dist: ipyplot; extra == "jupyter-metrics"
Requires-Dist: jupyter-dash; extra == "jupyter-metrics"
Requires-Dist: ipython<8.13; extra == "jupyter-metrics"
Provides-Extra: all
Requires-Dist: pandas; extra == "all"
Requires-Dist: crowd-kit>=1.0.0; extra == "all"
Requires-Dist: boto3>=1.4.7; extra == "all"
Requires-Dist: kazoo>=2.6.1; extra == "all"
Requires-Dist: plotly; extra == "all"
Requires-Dist: ipyplot; extra == "all"
Requires-Dist: jupyter-dash; extra == "all"
Requires-Dist: ipython<8.13; extra == "all"
